odoo/addons/product_standard_margin_kanban/__init__.py
odoo/addons/product_standard_margin_kanban/__manifest__.py
odoo/addons/product_standard_margin_kanban/i18n/es.po
odoo/addons/product_standard_margin_kanban/views/product_views.xml
odoo12_addon_product_standard_margin_kanban-12.0.1.0.1.dist-info/METADATA
odoo12_addon_product_standard_margin_kanban-12.0.1.0.1.dist-info/WHEEL
odoo12_addon_product_standard_margin_kanban-12.0.1.0.1.dist-info/top_level.txt
odoo12_addon_product_standard_margin_kanban-12.0.1.0.1.dist-info/RECORD
