Metadata-Version: 2.1
Name: odoo12-addon-product-standard-margin-kanban
Version: 12.0.1.0.1
Summary: Print Product Standard Margin Rate in Kanban view
Home-page: https://coopdevs.org
Author: Coopdevs Treball SCCL
License: AGPL-3
Platform: UNKNOWN
Classifier: Programming Language :: Python
Classifier: Framework :: Odoo
Classifier: Framework :: Odoo :: 12.0
Classifier: License :: OSI Approved :: GNU Affero General Public License v3
Requires-Python: >=3.5
Requires-Dist: odoo12-addon-product-standard-margin
Requires-Dist: odoo (<12.1dev,>=12.0a)
